{"guide_assets.md":"433234e8","guide_fetching.md":"02c4d35d","guide_index.md":"be50d985","guide_cookie.md":"6699f1ad","guide_plugins.md":"39027836","guide_redirect.md":"1e6a4e4c","guide_middleware.md":"2454e975","guide_modes.md":"263cde98","guide_entrypoint.md":"0cdf3685","guide_error.md":"2300ed65","api_components.md":"66bcea2d","guide_install.md":"96f68e4d","guide_build-deploy.md":"838f322f","api_context.md":"13f8dcc3","guide_store.md":"d987e726","index.md":"f754a901","api_index.md":"29066a4e","api_composables.md":"16f5439b","en_index.md":"8309cd28","guide_async.md":"49019e4a","guide_config.md":"25f83df9","guide_seo.md":"1cbef5aa","guide_state.md":"5befe4f4","guide_routing.md":"7b7b1ab1","api_plugins.md":"9264654b","guide_context.md":"6e1ec24a"}
